sbrunner_pre_commit_hooks/__init__.py
sbrunner_pre_commit_hooks/copyright.py
sbrunner_pre_commit_hooks/run_in_dir.py
sbrunner_pre_commit_hooks/workflow_timeout.py
sbrunner_pre_commit_hooks-0.2.3.dist-info/METADATA
sbrunner_pre_commit_hooks-0.2.3.dist-info/entry_points.txt
sbrunner_pre_commit_hooks-0.2.3.dist-info/WHEEL
sbrunner_pre_commit_hooks-0.2.3.dist-info/RECORD
