Metadata-Version: 2.1
Name: sbrunner-pre-commit-hooks
Version: 0.2.3
Summary: Pre commit hook by sbrunner
Home-page: https://github.com/sbrunner/pre-commit-hooks
Keywords: pre-commit
Author: Stéphane Brunner
Author-email: stephane.brunner@gmail.com
Requires-Python: >=3.8,<4.0
Classifier: Development Status :: 5 - Production/Stable
Classifier: Environment :: Console
Classifier: License :: OSI Approved :: BSD License
Classifier: Operating System :: OS Independent
Classifier: Programming Language :: Python
Classifier: Programming Language :: Python :: 3
Classifier: Programming Language :: Python :: 3.8
Classifier: Programming Language :: Python :: 3.9
Classifier: Programming Language :: Python :: 3.10
Classifier: Programming Language :: Python :: 3.11
Classifier: Programming Language :: Python :: 3
Classifier: Programming Language :: Python :: 3.10
Classifier: Programming Language :: Python :: 3.8
Classifier: Programming Language :: Python :: 3.9
Classifier: Typing :: Typed
Requires-Dist: PyYAML
Project-URL: Repository, https://github.com/sbrunner/pre-commit-hooks
